base58uuid/__init__.py
base58uuid/alphabet.py
base58uuid/decode.py
base58uuid/encode.py
base58uuid/uuid58.py
base58uuid-0.1.0.dist-info/METADATA
base58uuid-0.1.0.dist-info/WHEEL
base58uuid-0.1.0.dist-info/top_level.txt
base58uuid-0.1.0.dist-info/RECORD
