Metadata-Version: 2.4
Name: base58uuid
Version: 0.1.0
Summary: A tiny, zero-dependency Python library for generating and converting UUIDs to Base58-encoded strings
Home-page: https://github.com/htpboost/base58uuid
Author: Yoshitake Hatada
Author-email: yhatada@gingdang.co.jp
Classifier: Development Status :: 4 - Beta
Classifier: Intended Audience :: Developers
Classifier: License :: OSI Approved :: MIT License
Classifier: Programming Language :: Python :: 3
Classifier: Programming Language :: Python :: 3.7
Classifier: Programming Language :: Python :: 3.8
Classifier: Programming Language :: Python :: 3.9
Classifier: Programming Language :: Python :: 3.10
Classifier: Programming Language :: Python :: 3.11
Requires-Python: >=3.7
Dynamic: author
Dynamic: author-email
Dynamic: classifier
Dynamic: description
Dynamic: description-content-type
Dynamic: home-page
Dynamic: requires-python
Dynamic: summary
